<PAMDataset>
  <PAMRasterBand band="1">
    <Histograms>
      <HistItem>
        <HistMin>0.48048049211502</HistMin>
        <HistMax>212.84437561035</HistMax>
        <BucketCount>256</BucketCount>
        <IncludeOutOfRange>1</IncludeOutOfRange>
        <Approximate>0</Approximate>
        <HistCounts>5|10|13|19|19|24|30|34|38|40|42|51|57|52|66|68|72|67|80|85|86|86|96|94|105|105|103|117|119|120|135|119|138|144|136|149|145|156|162|151|175|168|169|182|188|188|188|193|205|198|203|212|209|229|223|239|239|224|239|256|241|254|265|268|265|274|265|269|260|256|251|261|264|245|254|269|257|265|268|267|267|270|278|263|277|276|268|291|278|289|296|267|307|298|292|301|311|303|312|311|314|321|314|334|326|331|342|330|343|345|352|356|361|360|361|373|376|369|386|389|384|413|398|405|412|418|402|433|430|428|480|534|598|654|744|778|819|869|919|963|1006|1077|1116|1153|1228|1289|1350|1382|1485|1542|1618|1648|1600|1563|1622|1640|1647|1643|1645|1653|1671|1812|1949|2117|2293|2454|2653|2900|3205|3449|4073|3377|3056|3002|2928|2937|2975|3207|3762|3195|2916|2778|2657|2628|2638|2675|2483|2415|2267|2190|2133|2030|1975|1951|1883|1866|1796|1802|1744|1737|1738|1689|1676|1696|1702|1725|1753|1928|1899|1688|1531|1440|1352|1287|1228|1166|1108|1084|1044|1015|949|892|840|780|511|342|313|304|289|269|268|254|232|226|207|197|195|167|160|152|139|123|119|105|91|79|74|57|39|34|30|24|17|11|5|1</HistCounts>
      </HistItem>
    </Histograms>
    <Metadata>
      <MDI key="STATISTICS_COVARIANCES">1224.140648392807</MDI>
      <MDI key="STATISTICS_MAXIMUM">212.84437561035</MDI>
      <MDI key="STATISTICS_MEAN">138.81079695689</MDI>
      <MDI key="STATISTICS_MINIMUM">0.48048049211502</MDI>
      <MDI key="STATISTICS_SKIPFACTORX">1</MDI>
      <MDI key="STATISTICS_SKIPFACTORY">1</MDI>
      <MDI key="STATISTICS_STDDEV">34.987721394695</MDI>
    </Metadata>
  </PAMRasterBand>
</PAMDataset>
