<?xml version="1.0" encoding="UTF-8"?>
<metadata xml:lang="es"><Esri><CreaDate>20231113</CreaDate><CreaTime>23382300</CreaTime><ArcGISFormat>1.0</ArcGISFormat><SyncOnce>TRUE</SyncOnce><DataProperties><lineage><Process ToolSource="c:\program files (x86)\arcgis\desktop10.8\ArcToolbox\Toolboxes\Spatial Analyst Tools.tbx\Kriging" Date="20231113" Time="233823">Kriging C:\Users\moise\OneDrive\Documents\PrecAnuales.shp F4 C:\Interpolaciones\PAnual2000.tif "Spherical 172.418888 63967.407448 608235.790460 0.000000" 100 "VARIABLE 12" #</Process></lineage></DataProperties></Esri></metadata>
